pytw/asset.py
pytw/advisory_vuln.py
pytw/search_params.py
pytw/core_vuln.py
pytw/pytw.py
pytw/__init__.py
pytw/impact_status.py
pytw/impact.py
pytw/cve_vuln.py
pytw/constants.py
pytw/remediation.py
pytw/rating.py
pytw/exploit.py
pytw/exceptions.py
pytw/client.py
pytw/impact_coll.py
pytw/asset_coll.py
pytw/product.py
pytw/cve_vuln_coll.py
pytw/patch.py
pytw-1.0.0.dist-info/metadata.json
pytw-1.0.0.dist-info/RECORD
pytw-1.0.0.dist-info/METADATA
pytw-1.0.0.dist-info/WHEEL
pytw-1.0.0.dist-info/top_level.txt
pytw-1.0.0.dist-info/DESCRIPTION.rst
