Metadata-Version: 2.0
Name: pytw
Version: 1.0.0
Summary: ThreatWatch opensource API
Home-page: https://github.com/opensource-tw/pytw
Author: Paresh Borkar
Author-email: opensource@threatwatch.io
License: GNU General Public License v3
Keywords: pytw
Platform: UNKNOWN
Classifier: Development Status :: 3 - Alpha
Classifier: Intended Audience :: Developers
Classifier: License :: OSI Approved :: GNU General Public License v3 (GPLv3)
Classifier: Natural Language :: English
Classifier: Programming Language :: Python :: 2
Classifier: Programming Language :: Python :: 2.7
Classifier: Programming Language :: Python :: 3
Classifier: Programming Language :: Python :: 3.4
Classifier: Programming Language :: Python :: 3.5
Classifier: Programming Language :: Python :: 3.6
Classifier: Programming Language :: Python :: 3.7
Requires-Dist: enum34
Requires-Dist: drest
